LICENSE
README.md
docs/images/csv_import_view.png
docs/images/menu.png
docs/images/onboarding_tasks_view.png
docs/images/single_device_form.png
netbox_onboarding/__init__.py
netbox_onboarding/admin.py
netbox_onboarding/api/__init__.py
netbox_onboarding/api/serializers.py
netbox_onboarding/api/urls.py
netbox_onboarding/api/views.py
netbox_onboarding/choices.py
netbox_onboarding/constants.py
netbox_onboarding/exceptions.py
netbox_onboarding/filters.py
netbox_onboarding/forms.py
netbox_onboarding/helpers.py
netbox_onboarding/metrics.py
netbox_onboarding/migrations/0001_initial.py
netbox_onboarding/migrations/0002_onboardingdevice.py
netbox_onboarding/migrations/0003_onboardingtask_change_logging_model.py
netbox_onboarding/migrations/0004_create_onboardingdevice.py
netbox_onboarding/migrations/__init__.py
netbox_onboarding/models.py
netbox_onboarding/navigation.py
netbox_onboarding/netbox_keeper.py
netbox_onboarding/netdev_keeper.py
netbox_onboarding/onboard.py
netbox_onboarding/onboarding/__init__.py
netbox_onboarding/onboarding/onboarding.py
netbox_onboarding/onboarding_extensions/__init__.py
netbox_onboarding/onboarding_extensions/ios.py
netbox_onboarding/release.py
netbox_onboarding/tables.py
netbox_onboarding/template_content.py
netbox_onboarding/templates/netbox_onboarding/device_onboarding_table.html
netbox_onboarding/templates/netbox_onboarding/onboarding_task_edit.html
netbox_onboarding/templates/netbox_onboarding/onboarding_tasks_list.html
netbox_onboarding/templates/netbox_onboarding/onboardingtask.html
netbox_onboarding/templates/netbox_onboarding/onboardingtask_ge210.html
netbox_onboarding/templates/netbox_onboarding/onboardingtask_lt210.html
netbox_onboarding/tests/__init__.py
netbox_onboarding/tests/test_api.py
netbox_onboarding/tests/test_models.py
netbox_onboarding/tests/test_netbox_keeper.py
netbox_onboarding/tests/test_netdev_keeper.py
netbox_onboarding/tests/test_views_28.py
netbox_onboarding/tests/test_views_29.py
netbox_onboarding/urls.py
ntc_netbox_plugin_onboarding-2.2.0.dist-info/LICENSE
ntc_netbox_plugin_onboarding-2.2.0.dist-info/WHEEL
ntc_netbox_plugin_onboarding-2.2.0.dist-info/METADATA
ntc_netbox_plugin_onboarding-2.2.0.dist-info/RECORD
