Metadata-Version: 2.1
Name: ntc-netbox-plugin-onboarding
Version: 2.2.0
Summary: A plugin for NetBox to easily onboard new devices.
Home-page: https://github.com/networktocode/ntc-netbox-plugin-onboarding
License: Apache-2.0
Keywords: netbox,network,onboarding,django
Author: Network to Code, LLC
Author-email: info@networktocode.com
Requires-Python: >=3.6,<4.0
Classifier: License :: OSI Approved :: Apache Software License
Classifier: Programming Language :: Python :: 3
Classifier: Programming Language :: Python :: 3.6
Classifier: Programming Language :: Python :: 3.7
Classifier: Programming Language :: Python :: 3.8
Requires-Dist: napalm (>=2.5.0,<4)
Requires-Dist: zipp (>=3.4.0,<4.0.0)
Project-URL: Repository, https://github.com/networktocode/ntc-netbox-plugin-onboarding
